skein/__init__.py
skein/_version.py
skein/cli.py
skein/core.py
skein/exceptions.py
skein/kv.py
skein/model.py
skein/objects.py
skein/tornado.py
skein/ui.py
skein/utils.py
skein/java/skein.jar
skein/proto/__init__.py
skein/proto/skein_pb2.py
skein/proto/skein_pb2_grpc.py
skein/recipes/__init__.py
skein/recipes/ipython_kernel.py
skein/recipes/jupyter_notebook.py
skein-0.8.2.dist-info/LICENSE
skein-0.8.2.dist-info/METADATA
skein-0.8.2.dist-info/WHEEL
skein-0.8.2.dist-info/entry_points.txt
skein-0.8.2.dist-info/top_level.txt
skein-0.8.2.dist-info/RECORD
