Metadata-Version: 2.1
Name: skein
Version: 0.8.2
Summary: A simple tool and library for deploying applications on Apache YARN
Home-page: https://jcristharif.com/skein/
Maintainer: Jim Crist-Harif
Maintainer-email: jcristharif@gmail.com
License: BSD
Project-URL: Documentation, https://jcristharif.com/skein/
Project-URL: Source, https://github.com/jcrist/skein/
Project-URL: Issue Tracker, https://github.com/jcrist/skein/issues
Keywords: YARN HDFS hadoop distributed cluster
Platform: UNKNOWN
Classifier: Development Status :: 5 - Production/Stable
Classifier: License :: OSI Approved :: BSD License
Classifier: Programming Language :: Java
Classifier: Programming Language :: Python :: 3.5
Classifier: Programming Language :: Python :: 3.6
Classifier: Programming Language :: Python :: 3.7
Classifier: Topic :: Software Development :: Libraries :: Java Libraries
Classifier: Topic :: System :: Systems Administration
Classifier: Topic :: System :: Distributed Computing
Requires-Python: >=3.5
License-File: LICENSE
Requires-Dist: grpcio (!=1.45.0,>=1.11.0)
Requires-Dist: protobuf (>=3.5.0)
Requires-Dist: pyyaml
Requires-Dist: cryptography
